mobi_motion_tracking/__init__.py
mobi_motion_tracking/__main__.py
mobi_motion_tracking/core/__init__.py
mobi_motion_tracking/core/cli.py
mobi_motion_tracking/core/models.py
mobi_motion_tracking/core/orchestrator.py
mobi_motion_tracking/io/__init__.py
mobi_motion_tracking/io/readers/.DS_Store
mobi_motion_tracking/io/readers/__init__.py
mobi_motion_tracking/io/readers/readers.py
mobi_motion_tracking/io/writers/__init__.py
mobi_motion_tracking/io/writers/writers.py
mobi_motion_tracking/preprocessing/__init__.py
mobi_motion_tracking/preprocessing/joint_index_list.py
mobi_motion_tracking/preprocessing/preprocessing.py
mobi_motion_tracking/processing/__init__.py
mobi_motion_tracking/processing/similarity_functions.py
mobi_motion_tracking-0.1.2.dist-info/LICENSE
mobi_motion_tracking-0.1.2.dist-info/METADATA
mobi_motion_tracking-0.1.2.dist-info/WHEEL
mobi_motion_tracking-0.1.2.dist-info/entry_points.txt
mobi_motion_tracking-0.1.2.dist-info/RECORD
