Metadata-Version: 2.3
Name: mobi_motion_tracking
Version: 0.1.2
Summary: python package to process 3d motion tracking data
License: GNU Lesser General Public License v2.1
Author: Celia Maiorano
Author-email: celia.maiorano@childmind.org
Requires-Python: >=3.11
Classifier: License :: Other/Proprietary License
Classifier: Programming Language :: Python :: 3
Classifier: Programming Language :: Python :: 3.11
Classifier: Programming Language :: Python :: 3.12
Classifier: Programming Language :: Python :: 3.13
Requires-Dist: openpyxl (>=3.1.5,<4.0.0)
Requires-Dist: pandas (>=2.2.3,<3.0.0)
Requires-Dist: pytest (>=8.3.4,<9.0.0)
Requires-Dist: pytest-mock (>=3.14.0,<4.0.0)
